[
    {
        "register_no": "25UBC101",
        "name": "AARUSH MANOJ",
        "email": "aarush.25ubc101@mariancollege.org"
    },
    {
        "register_no": "25UBC102",
        "name": "ABHINANDHU T R",
        "email": "abhinandhu.25ubc102@mariancollege.org"
    },
    {
        "register_no": "25UBC103",
        "name": "AKSA ELIZABETH BINU",
        "email": "aksa.25ubc103@mariancollege.org"
    },
    {
        "register_no": "25UBC104",
        "name": "ALAN ROBIN",
        "email": "alan.25ubc104@mariancollege.org"
    },
    {
        "register_no": "25UBC105",
        "name": "ALEENA BINOY",
        "email": "aleena.25ubc105@mariancollege.org"
    },
    {
        "register_no": "25UBC106",
        "name": "AMRUTHA RATHEESH",
        "email": "amrutha.25ubc106@mariancollege.org"
    },
    {
        "register_no": "25UBC107",
        "name": "ANGEL ROSE SHAIBU",
        "email": "angel.25ubc107@mariancollege.org"
    },
    {
        "register_no": "25UBC108",
        "name": "ANON JOSEPH",
        "email": "anon.25ubc108@mariancollege.org"
    },
    {
        "register_no": "25UBC109",
        "name": "ARJUN S KUMAR",
        "email": "arjun.25ubc109@mariancollege.org"
    },
    {
        "register_no": "25UBC110",
        "name": "ARUNIMA BABU",
        "email": "arunima.25ubc110@mariancollege.org"
    },
    {
        "register_no": "25UBC111",
        "name": "ASHA BENNY",
        "email": "asha.25ubc111@mariancollege.org"
    },
    {
        "register_no": "25UBC112",
        "name": "ASWIN SUDHAKARAN",
        "email": "aswin.25ubc112@mariancollege.org"
    },
    {
        "register_no": "25UBC113",
        "name": "ATHIRA ANIL",
        "email": "athira.25ubc113@mariancollege.org"
    },
    {
        "register_no": "25UBC114",
        "name": "ATHIRA DAS",
        "email": "athira.25ubc114@mariancollege.org"
    },
    {
        "register_no": "25UBC116",
        "name": "BEN GEORGE SABU",
        "email": "ben.25ubc116@mariancollege.org"
    },
    {
        "register_no": "25UBC117",
        "name": "BINITHA WILSON",
        "email": "binitha.25ubc117@mariancollege.org"
    },
    {
        "register_no": "25UBC118",
        "name": "CIS MARIA VARGHESE",
        "email": "cis.25ubc118@mariancollege.org"
    },
    {
        "register_no": "25UBC119",
        "name": "DEENA SONEY",
        "email": "deena.25ubc119@mariancollege.org"
    },
    {
        "register_no": "25UBC120",
        "name": "DELLA ANN JOSHI",
        "email": "della.25ubc120@mariancollege.org"
    },
    {
        "register_no": "25UBC121",
        "name": "DELNA BENOY",
        "email": "delna.25ubc121@mariancollege.org"
    },
    {
        "register_no": "25UBC123",
        "name": "DEVARSH S",
        "email": "devarsh.25ubc123@mariancollege.org"
    },
    {
        "register_no": "25UBC124",
        "name": "DHANYA LATHESH",
        "email": "dhanya.25ubc124@mariancollege.org"
    },
    {
        "register_no": "25UBC125",
        "name": "DHANYA V",
        "email": "dhanya.25ubc125@mariancollege.org"
    },
    {
        "register_no": "25UBC126",
        "name": "ELAINE MARIA GEORGE",
        "email": "elaine.25ubc126@mariancollege.org"
    },
    {
        "register_no": "25UBC127",
        "name": "FEBI SUSAN SAJAN",
        "email": "febi.25ubc127@mariancollege.org"
    },
    {
        "register_no": "25UBC128",
        "name": "HARINI S",
        "email": "harini.25ubc128@mariancollege.org"
    },
    {
        "register_no": "25UBC129",
        "name": "IRIS DAIN",
        "email": "iris.25ubc129@mariancollege.org"
    },
    {
        "register_no": "25UBC130",
        "name": "JENISHA M",
        "email": "jenisha.25ubc130@mariancollege.org"
    },
    {
        "register_no": "25UBC131",
        "name": "JERIT GEORGE",
        "email": "jerit.25ubc131@mariancollege.org"
    },
    {
        "register_no": "25UBC132",
        "name": "JIBIN BENNY",
        "email": "jibin.25ubc132@mariancollege.org"
    },
    {
        "register_no": "25UBC133",
        "name": "JISNA BINOY",
        "email": "jisna.25ubc133@mariancollege.org"
    },
    {
        "register_no": "25UBC134",
        "name": "JOSEPH ALEN SAJEEV",
        "email": "joseph.25ubc134@mariancollege.org"
    },
    {
        "register_no": "25UBC135",
        "name": "JOYAL JOSE",
        "email": "joyal.25ubc135@mariancollege.org"
    },
    {
        "register_no": "25UBC136",
        "name": "KARTHIKA JAYAN",
        "email": "karthika.25ubc136@mariancollege.org"
    },
    {
        "register_no": "25UBC137",
        "name": "KEERTHANA HARIKUMAR",
        "email": "keerthana.25ubc137@mariancollege.org"
    },
    {
        "register_no": "25UBC138",
        "name": "LIYA LUKOSE",
        "email": "liya.25ubc138@mariancollege.org"
    },
    {
        "register_no": "25UBC139",
        "name": "MATHEWS BASIL",
        "email": "mathews.25ubc139@mariancollege.org"
    },
    {
        "register_no": "25UBC140",
        "name": "MIBIN SIBY",
        "email": "mibin.25ubc140@mariancollege.org"
    },
    {
        "register_no": "25UBC141",
        "name": "MOHAMED NUHAN",
        "email": "mohamed.25ubc141@mariancollege.org"
    },
    {
        "register_no": "25UBC142",
        "name": "MUHAMMED NEBIL",
        "email": "muhammed.25ubc142@mariancollege.org"
    },
    {
        "register_no": "25UBC143",
        "name": "NADIA JALEEL",
        "email": "nadia.25ubc143@mariancollege.org"
    },
    {
        "register_no": "25UBC144",
        "name": "NAVYA M",
        "email": "navya.25ubc144@mariancollege.org"
    },
    {
        "register_no": "25UBC145",
        "name": "NEHA",
        "email": "neha.25ubc145@mariancollege.org"
    },
    {
        "register_no": "25UBC146",
        "name": "NEHA VINOD",
        "email": "neha.25ubc146@mariancollege.org"
    },
    {
        "register_no": "25UBC147",
        "name": "RIYA ROSE MANOJ",
        "email": "riya.25ubc147@mariancollege.org"
    },
    {
        "register_no": "25UBC148",
        "name": "SEBASTIAN GEORGE P G",
        "email": "sebastian.25ubc148@mariancollege.org"
    },
    {
        "register_no": "25UBC149",
        "name": "SHARON SABU",
        "email": "sharon.25ubc149@mariancollege.org"
    },
    {
        "register_no": "25UBC150",
        "name": "SHERIN THOMAS",
        "email": "sherin.25ubc150@mariancollege.org"
    },
    {
        "register_no": "25UBC152",
        "name": "SIVANANDHITHA ARUN",
        "email": "sivanandhitha.25ubc152@mariancollege.org"
    },
    {
        "register_no": "25UBC153",
        "name": "SRAVYALAKSHMI SUNIL",
        "email": "sravyalakshmi.25ubc153@mariancollege.org"
    },
    {
        "register_no": "25UBC154",
        "name": "SREELAKSHMI S NAIR",
        "email": "sreelakshmi.25ubc154@mariancollege.org"
    },
    {
        "register_no": "25UBC155",
        "name": "STEEV TOM BIJU",
        "email": "steev.25ubc155@mariancollege.org"
    },
    {
        "register_no": "25UBC156",
        "name": "SUBHALEKSHMI P",
        "email": "subhalekshmi.25ubc156@mariancollege.org"
    },
    {
        "register_no": "25UBC157",
        "name": "SWATHIKA S NARAYAN",
        "email": "swathika.25ubc157@mariancollege.org"
    },
    {
        "register_no": "25UBC158",
        "name": "TERES ANNA ANTONY",
        "email": "teres.25ubc158@mariancollege.org"
    },
    {
        "register_no": "25UBC159",
        "name": "VIVEK JOBY",
        "email": "vivek.25ubc159@mariancollege.org"
    },
    {
        "register_no": "25UBC160",
        "name": "Y DANY EMMANUEL",
        "email": "dany.25ubc160@mariancollege.org"
    },
    {
        "register_no": "25UBC161",
        "name": "ANEETA JUSTINE",
        "email": "aneeta.25ubc161@mariancollege.org"
    }
]